NoJobsMath/__init__.py
NoJobsMath-1.0.0.dist-info/METADATA
NoJobsMath-1.0.0.dist-info/WHEEL
NoJobsMath-1.0.0.dist-info/top_level.txt
NoJobsMath-1.0.0.dist-info/RECORD
